SpringMvcKuangjiaRumenjiaochengCYuyanBianchengWang/README.md
SpringMvcKuangjiaRumenjiaochengCYuyanBianchengWang/__init__.py
SpringMvcKuangjiaRumenjiaochengCYuyanBianchengWang/__main__.py
SpringMvcKuangjiaRumenjiaochengCYuyanBianchengWang/file.epub
SpringMvcKuangjiaRumenjiaochengCYuyanBianchengWang/index.html
SpringMvcKuangjiaRumenjiaochengCYuyanBianchengWang/css/__init__.py
SpringMvcKuangjiaRumenjiaochengCYuyanBianchengWang/css/annotations.css
SpringMvcKuangjiaRumenjiaochengCYuyanBianchengWang/css/main.css
SpringMvcKuangjiaRumenjiaochengCYuyanBianchengWang/css/normalize.css
SpringMvcKuangjiaRumenjiaochengCYuyanBianchengWang/css/popup.css
SpringMvcKuangjiaRumenjiaochengCYuyanBianchengWang/font/__init__.py
SpringMvcKuangjiaRumenjiaochengCYuyanBianchengWang/font/fontello.eot
SpringMvcKuangjiaRumenjiaochengCYuyanBianchengWang/font/fontello.svg
SpringMvcKuangjiaRumenjiaochengCYuyanBianchengWang/font/fontello.ttf
SpringMvcKuangjiaRumenjiaochengCYuyanBianchengWang/font/fontello.woff
SpringMvcKuangjiaRumenjiaochengCYuyanBianchengWang/img/__init__.py
SpringMvcKuangjiaRumenjiaochengCYuyanBianchengWang/img/annotator-glyph-sprite.png
SpringMvcKuangjiaRumenjiaochengCYuyanBianchengWang/img/annotator-icon-sprite.png
SpringMvcKuangjiaRumenjiaochengCYuyanBianchengWang/img/apple-touch-icon.png
SpringMvcKuangjiaRumenjiaochengCYuyanBianchengWang/img/cancelfullscreen.png
SpringMvcKuangjiaRumenjiaochengCYuyanBianchengWang/img/close.png
SpringMvcKuangjiaRumenjiaochengCYuyanBianchengWang/img/fullscreen.png
SpringMvcKuangjiaRumenjiaochengCYuyanBianchengWang/img/loader.gif
SpringMvcKuangjiaRumenjiaochengCYuyanBianchengWang/img/menu-icon.png
SpringMvcKuangjiaRumenjiaochengCYuyanBianchengWang/img/save.png
SpringMvcKuangjiaRumenjiaochengCYuyanBianchengWang/img/saved.png
SpringMvcKuangjiaRumenjiaochengCYuyanBianchengWang/img/settings-s.png
SpringMvcKuangjiaRumenjiaochengCYuyanBianchengWang/img/settings.png
SpringMvcKuangjiaRumenjiaochengCYuyanBianchengWang/img/star.png
spring_mvc_kuangjia_rumenjiaocheng_c_yuyan_biancheng_wang-2024.3.5.0.dist-info/METADATA
spring_mvc_kuangjia_rumenjiaocheng_c_yuyan_biancheng_wang-2024.3.5.0.dist-info/WHEEL
spring_mvc_kuangjia_rumenjiaocheng_c_yuyan_biancheng_wang-2024.3.5.0.dist-info/entry_points.txt
spring_mvc_kuangjia_rumenjiaocheng_c_yuyan_biancheng_wang-2024.3.5.0.dist-info/top_level.txt
spring_mvc_kuangjia_rumenjiaocheng_c_yuyan_biancheng_wang-2024.3.5.0.dist-info/RECORD
